spargear/__init__.py
spargear/_typing.py
spargear/argspec.py
spargear/arguments.py
spargear/base.py
spargear/py.typed
spargear/subcommand.py
spargear-0.2.20.dist-info/METADATA
spargear-0.2.20.dist-info/WHEEL
spargear-0.2.20.dist-info/top_level.txt
spargear-0.2.20.dist-info/RECORD
