Metadata-Version: 2.4
Name: spargear
Version: 0.2.20
Summary: Declarative and typed argument parsing built on argparse.
License-Expression: MIT
Project-URL: repository, https://github.com/c0sogi/spargear
Requires-Python: >=3.8
Requires-Dist: typing-extensions>=3.10; python_full_version < "3.9"
Provides-Extra: dev
Requires-Dist: pyright>=1.1.401; extra == "dev"
